text_align/__init__.py
text_align/text_align.py
text_align-1.0.5.dist-info/LICENCE
text_align-1.0.5.dist-info/METADATA
text_align-1.0.5.dist-info/WHEEL
text_align-1.0.5.dist-info/top_level.txt
text_align-1.0.5.dist-info/RECORD
