Metadata-Version: 2.1
Name: text_align
Version: 1.0.5
Summary: This module allows you to align text relative to the center, right, left and both sides
Home-page: https://github.com/ej-you/TextAlign
Author: Ejyou
Author-email: ejyou.user@gmail.com
Keywords: text_align python
Classifier: Programming Language :: Python :: 3.12
Classifier: License :: OSI Approved :: MIT License
Classifier: Operating System :: OS Independent
Requires-Python: >=3.7
License-File: LICENCE
